gmx_rrcs-1.0.5.dist-info/licenses/LICENSE
packages/__init__.py
packages/constants.py
packages/gmx_rrcs.py
packages/gmxout2csv.py
packages/plot_line.py
packages/plot_rrcs_count.py
packages/rrcs_visualizer.py
packages/utilities.py
gmx_rrcs-1.0.5.dist-info/METADATA
gmx_rrcs-1.0.5.dist-info/WHEEL
gmx_rrcs-1.0.5.dist-info/entry_points.txt
gmx_rrcs-1.0.5.dist-info/top_level.txt
gmx_rrcs-1.0.5.dist-info/RECORD
