Metadata-Version: 2.4
Name: gmx_RRCS
Version: 1.0.5
Summary: The gmx_RRCS script is designed to calculate the residues-residues contact scores (RRCS) from a trajectory file generated by GROMACS.
Home-page: https://github.com/RuijinHospitalRCMSB/gmx_RRCS.git
Author: Wei Han, Zhenghan Chen, Ming-wei Wang, Qingtong Zhou
Author-email: iqtzhou@gmail.com, whanwei@foxmail.com
Classifier: Programming Language :: Python :: 3
Classifier: License :: OSI Approved :: MIT License
Classifier: Operating System :: OS Independent
Requires-Python: >=3.9
License-File: LICENSE
Requires-Dist: colorama>=0.4.6
Requires-Dist: matplotlib>=3.7.1
Requires-Dist: MDAnalysis>=2.4.3
Requires-Dist: numba>=0.60.0
Requires-Dist: numpy>=1.23.5
Requires-Dist: packaging>=24.1
Requires-Dist: seaborn>=0.13.2
Requires-Dist: termcolor>=2.4.0
Dynamic: author
Dynamic: author-email
Dynamic: classifier
Dynamic: description
Dynamic: description-content-type
Dynamic: home-page
Dynamic: license-file
Dynamic: requires-dist
Dynamic: requires-python
Dynamic: summary
